crepe_notes/__init__.py
crepe_notes/cli.py
crepe_notes/crepe_notes.py
crepe_notes-0.1.3.dist-info/AUTHORS.rst
crepe_notes-0.1.3.dist-info/LICENSE
crepe_notes-0.1.3.dist-info/METADATA
crepe_notes-0.1.3.dist-info/WHEEL
crepe_notes-0.1.3.dist-info/entry_points.txt
crepe_notes-0.1.3.dist-info/top_level.txt
crepe_notes-0.1.3.dist-info/RECORD
