Metadata-Version: 2.1
Name: crepe-notes
Version: 0.1.3
Summary: Post-processing for CREPE to turn f0 pitch estimates into discrete notes e.g. MIDI
Home-page: https://github.com/xavriley/crepe_notes
Author: Xavier Riley
Author-email: xavriley@hotmail.com
License: GNU General Public License v3.0 license
Keywords: crepe_notes
Platform: UNKNOWN
Classifier: Development Status :: 4 - Beta
Classifier: Intended Audience :: Science/Research
Classifier: License :: OSI Approved :: GNU General Public License v3 or later (GPLv3+)
Classifier: Natural Language :: English
Classifier: Programming Language :: Python :: 3
Classifier: Programming Language :: Python :: 3.6
Classifier: Programming Language :: Python :: 3.7
Classifier: Programming Language :: Python :: 3.8
Requires-Python: >=3.6
License-File: LICENSE
License-File: AUTHORS.rst
Requires-Dist: Click (>=7.0)
Requires-Dist: librosa (>=0.7.2)
Requires-Dist: numpy (>=1.20.3)
Requires-Dist: madmom
Requires-Dist: pretty-midi
Requires-Dist: crepe
